{"chunk_definitions":[{"row":95,"row_count":1,"visible":true,"expansion_state":0,"options":{"engine":"r","include":false,"label":"unnamed-chunk-2","dev":"png"},"document_id":"80CE8238","chunk_id":"cg0as7gdbagc3","chunk_label":"unnamed-chunk-5"},{"row":109,"row_count":1,"visible":true,"expansion_state":0,"options":{"engine":"r","label":"unnamed-chunk-3","dev":"png"},"document_id":"80CE8238","chunk_id":"cmwslhd0ntych","chunk_label":"unnamed-chunk-6"},{"row":127,"row_count":1,"visible":true,"expansion_state":0,"options":{"engine":"r","label":"unnamed-chunk-4","dev":"png"},"document_id":"80CE8238","chunk_id":"cnjncjo0mlazk","chunk_label":"unnamed-chunk-7"},{"row":135,"row_count":1,"visible":true,"expansion_state":0,"options":{"engine":"r","label":"unnamed-chunk-5","dev":"png"},"document_id":"80CE8238","chunk_id":"chn57c6coxqig","chunk_label":"unnamed-chunk-8"}],"doc_write_time":1718756184,"chunk_rendered_width":700}